brainsatplay/__init__.py
brainsatplay-0.1.2.dist-info/LICENSE
brainsatplay-0.1.2.dist-info/METADATA
brainsatplay-0.1.2.dist-info/WHEEL
brainsatplay-0.1.2.dist-info/top_level.txt
brainsatplay-0.1.2.dist-info/RECORD
