Metadata-Version: 2.1
Name: brainsatplay
Version: 0.1.2
Summary: A Python library for interfacing with Brains@Play
Home-page: https://github.com/brainsatplay/brainsatplay.js
Author: Garrett Flynn
Author-email: gflynn@usc.edu
License: gpl-3.0
Keywords: BCI,neuroscience
Platform: UNKNOWN
Classifier: Development Status :: 3 - Alpha
Classifier: Intended Audience :: Developers
Classifier: License :: OSI Approved :: GNU General Public License v3 (GPLv3)
Classifier: Programming Language :: Python :: 3.8
Requires-Dist: websockets
Requires-Dist: ssl
